Ligare/__init__.py
Ligare/AWS/__init__.py
Ligare/AWS/py.typed
Ligare/AWS/ssm.py
Ligare/GitHub/__init__.py
Ligare/GitHub/api.py
Ligare/GitHub/py.typed
Ligare/database/__init__.py
Ligare/database/config.py
Ligare/database/dependency_injection.py
Ligare/database/py.typed
Ligare/database/types.py
Ligare/development/__init__.py
Ligare/development/profiling.py
Ligare/development/py.typed
Ligare/identity/__init__.py
Ligare/identity/config.py
Ligare/identity/dependency_injection.py
Ligare/identity/py.typed
Ligare/platform/__init__.py
Ligare/platform/dependency_injection.py
Ligare/platform/py.typed
Ligare/programming/__init__.py
Ligare/programming/application.py
Ligare/programming/dependency_injection.py
Ligare/programming/exception.py
Ligare/programming/py.typed
Ligare/testing/__init__.py
Ligare/testing/py.typed
Ligare/web/__init__.py
Ligare/web/application.py
Ligare/web/config.py
Ligare/web/py.typed
Ligare/web/response.py
ligare_all-0.10.3.dist-info/licenses/LICENSE.md
ligare_all-0.10.3.dist-info/METADATA
ligare_all-0.10.3.dist-info/WHEEL
ligare_all-0.10.3.dist-info/top_level.txt
ligare_all-0.10.3.dist-info/RECORD
