Metadata-Version: 2.4
Name: Ligare.all
Version: 0.10.3
Summary: A framework for quickly developing new Python applications.
Author-email: Aaron Holmes <aholmes@mednet.ucla.edu>
Project-URL: Homepage, https://github.com/uclahs-cds/Ligare
Project-URL: Bug Tracker, https://github.com/uclahs-cds/Ligare/issues
Project-URL: Repository, https://github.com/uclahs-cds/Ligare.git
Project-URL: Changelog, https://github.com/uclahs-cds/Ligare/blob/main/CHANGELOG.md
Classifier: Programming Language :: Python :: 3
Classifier: License :: OSI Approved :: GNU General Public License (GPL)
Classifier: Operating System :: OS Independent
Classifier: Topic :: Scientific/Engineering
Classifier: Topic :: Software Development :: Libraries
Classifier: Topic :: Software Development :: Libraries :: Application Frameworks
Classifier: Intended Audience :: Science/Research
Classifier: Intended Audience :: Developers
Classifier: Development Status :: 4 - Beta
Classifier: Natural Language :: English
Requires-Python: >=3.10
License-File: LICENSE.md
Requires-Dist: Ligare.AWS
Requires-Dist: Ligare.database
Requires-Dist: Ligare.development
Requires-Dist: Ligare.GitHub
Requires-Dist: Ligare.identity
Requires-Dist: Ligare.platform
Requires-Dist: Ligare.programming
Requires-Dist: Ligare.testing
Requires-Dist: Ligare.web
Provides-Extra: dev-dependencies
Requires-Dist: tox~=4.18; extra == "dev-dependencies"
Requires-Dist: pytest~=8.0; extra == "dev-dependencies"
Requires-Dist: pytest-mock; extra == "dev-dependencies"
Requires-Dist: mock; extra == "dev-dependencies"
Requires-Dist: pytest-cov<7.0,>=4.1; extra == "dev-dependencies"
Requires-Dist: coverage~=7.4; extra == "dev-dependencies"
Requires-Dist: junit2html<32.0,>=30.1; extra == "dev-dependencies"
Requires-Dist: pyright==1.1.401; extra == "dev-dependencies"
Requires-Dist: isort<7.0,>=5.13; extra == "dev-dependencies"
Requires-Dist: ruff~=0.3; extra == "dev-dependencies"
Requires-Dist: bandit[sarif,toml]~=1.7; extra == "dev-dependencies"
Requires-Dist: sphinx; extra == "dev-dependencies"
Requires-Dist: sphinx-autodoc-typehints; extra == "dev-dependencies"
Requires-Dist: sphinx_toolbox; extra == "dev-dependencies"
Requires-Dist: sphinx-rtd-theme; extra == "dev-dependencies"
Requires-Dist: sphinx-copybutton; extra == "dev-dependencies"
Requires-Dist: sphinx-autobuild; extra == "dev-dependencies"
Requires-Dist: sphinxcontrib-plantuml; extra == "dev-dependencies"
Provides-Extra: vscode-sphinx
Requires-Dist: esbonio; extra == "vscode-sphinx"
Dynamic: license-file
